__init__.py
detector.py
main.py
tracker.py
utils/__init__.py
utils/datetime_utils.py
utils/enums.py
utils/image_utils.py
py_person_detector-0.0.1.dist-info/LICENSE.md
py_person_detector-0.0.1.dist-info/METADATA
py_person_detector-0.0.1.dist-info/WHEEL
py_person_detector-0.0.1.dist-info/top_level.txt
py_person_detector-0.0.1.dist-info/RECORD
