Metadata-Version: 2.1
Name: py_person_detector
Version: 0.0.1
Summary: A high level API for detecting and tracking people.
Author-email: k3y5tr0k3 <k3y5tr0k3.software@gmail.com>
Project-URL: Homepage, https://github.com/k3y5tr0k3/person-detector
Project-URL: Issues, https://github.com/k3y5tr0k3/person-detector/issues
Classifier: Programming Language :: Python :: 3
Classifier: License :: OSI Approved :: GNU Affero General Public License v3
Classifier: Operating System :: OS Independent
Requires-Python: >=3.10
License-File: LICENSE.md
